spark_fuse/__init__.py
spark_fuse/spark.py
spark_fuse/io/__init__.py
spark_fuse/io/qdrant.py
spark_fuse/io/rest_api.py
spark_fuse/io/sparql.py
spark_fuse/io/utils.py
spark_fuse/similarity/__init__.py
spark_fuse/similarity/choices.py
spark_fuse/similarity/embedding.py
spark_fuse/similarity/metrics.py
spark_fuse/similarity/partitioners.py
spark_fuse/similarity/pipeline.py
spark_fuse/tools/__init__.py
spark_fuse/tools/cli.py
spark_fuse/utils/__init__.py
spark_fuse/utils/change_tracking.py
spark_fuse/utils/dataframe.py
spark_fuse/utils/logging.py
spark_fuse/utils/transformations.py
spark_fuse-1.0.3.dist-info/METADATA
spark_fuse-1.0.3.dist-info/WHEEL
spark_fuse-1.0.3.dist-info/entry_points.txt
spark_fuse-1.0.3.dist-info/licenses/LICENSE
spark_fuse-1.0.3.dist-info/RECORD
