Metadata-Version: 2.4
Name: spark-fuse
Version: 1.0.3
Summary: Open-source PySpark toolkit with data sources for REST APIs and SPARQL endpoints.
Project-URL: Homepage, https://kevinsames.github.io/spark-fuse/
Project-URL: Documentation, https://kevinsames.github.io/spark-fuse/
Project-URL: Repository, https://github.com/kevinsames/spark-fuse
Project-URL: Issues, https://github.com/kevinsames/spark-fuse/issues
Author: Kevin Sames
License: Copyright 2025 Kevin Sames
License-File: LICENSE
Classifier: License :: OSI Approved :: Apache Software License
Classifier: Operating System :: OS Independent
Classifier: Programming Language :: Python :: 3
Classifier: Programming Language :: Python :: 3 :: Only
Classifier: Programming Language :: Python :: 3.9
Classifier: Programming Language :: Python :: 3.10
Classifier: Programming Language :: Python :: 3.11
Classifier: Programming Language :: Python :: 3.12
Requires-Python: >=3.9
Requires-Dist: adlfs>=2023.4
Requires-Dist: azure-identity>=1.14
Requires-Dist: delta-spark<5,>=4
Requires-Dist: numpy<3,>=2
Requires-Dist: pandas<3,>=2
Requires-Dist: pyarrow>=14
Requires-Dist: pydantic>=2
Requires-Dist: pyspark<5,>=4
Requires-Dist: requests>=2
Requires-Dist: rich>=13
Requires-Dist: sentence-transformers>=2.5
Requires-Dist: typer>=0.9
Provides-Extra: dev
Requires-Dist: build>=1; extra == 'dev'
Requires-Dist: pre-commit>=3; extra == 'dev'
Requires-Dist: pytest-cov>=4; extra == 'dev'
Requires-Dist: pytest>=7; extra == 'dev'
Requires-Dist: ruff>=0.4; extra == 'dev'
Requires-Dist: twine>=5; extra == 'dev'
